{
  "resourceType" : "CodeSystem",
  "id" : "vaktsiinvalditavad-haigused--5",
  "language" : "et",
  "url" : "https://fhir.ee/CodeSystem/vaktsiinvalditavad-haigused",
  "identifier" : [ {
    "system" : "urn:ietf:rfc:3986",
    "value" : "urn:oid:1.3.6.1.4.1.28284.6.2.1.278"
  }, {
    "type" : {
      "coding" : [ {
        "code" : "version"
      } ]
    },
    "system" : "urn:ietf:rfc:3986",
    "value" : "urn:oid:1.3.6.1.4.1.28284.6.2.1.278.5"
  } ],
  "version" : "5",
  "versionAlgorithmString" : "integer",
  "name" : "VaktsiinvalditavadHaigused",
  "title" : "Vaktsiinvälditavad haigused ja haigustekitajad",
  "status" : "draft",
  "experimental" : false,
  "date" : "2022-08-31T00:00:00Z",
  "publisher" : "TEHIK",
  "contact" : [ {
    "telecom" : [ {
      "system" : "email",
      "value" : "andmekorraldus@tehik.ee"
    }, {
      "system" : "url",
      "value" : "https://tehik.ee/"
    } ]
  } ],
  "description" : "Vaktsiinvälditavad haigused ja haigustekitajad - kasutatakse siis, kui arst edastab patsiendi vaktsineerimise andmeid.",
  "endorser" : [ {
    "name" : "Terviseamet"
  } ],
  "caseSensitive" : false,
  "content" : "complete",
  "property" : [ {
    "code" : "display",
    "uri" : "http://terminology.hl7.org/CodeSystem/designation-usage|display",
    "description" : "Display",
    "type" : "string"
  }, {
    "code" : "status",
    "uri" : "http://hl7.org/fhir/concept-properties#status",
    "description" : "Status",
    "type" : "code"
  } ],
  "concept" : [ {
    "code" : "101",
    "display" : "B-viirushepatiit",
    "property" : [ {
      "code" : "status",
      "valueCode" : "active"
    } ]
  }, {
    "code" : "102",
    "display" : "difteeria",
    "property" : [ {
      "code" : "status",
      "valueCode" : "active"
    } ]
  }, {
    "code" : "103",
    "display" : "hemofiilus-nakkus",
    "property" : [ {
      "code" : "status",
      "valueCode" : "active"
    } ]
  }, {
    "code" : "104",
    "display" : "leetrid",
    "property" : [ {
      "code" : "status",
      "valueCode" : "active"
    } ]
  }, {
    "code" : "105",
    "display" : "läkaköha",
    "property" : [ {
      "code" : "status",
      "valueCode" : "active"
    } ]
  }, {
    "code" : "106",
    "display" : "mumps",
    "property" : [ {
      "code" : "status",
      "valueCode" : "active"
    } ]
  }, {
    "code" : "107",
    "display" : "poliomüeliit",
    "property" : [ {
      "code" : "status",
      "valueCode" : "active"
    } ]
  }, {
    "code" : "108",
    "display" : "punetised",
    "property" : [ {
      "code" : "status",
      "valueCode" : "active"
    } ]
  }, {
    "code" : "109",
    "display" : "teetanus",
    "property" : [ {
      "code" : "status",
      "valueCode" : "active"
    } ]
  }, {
    "code" : "110",
    "display" : "tuberkuloos",
    "property" : [ {
      "code" : "status",
      "valueCode" : "active"
    } ]
  }, {
    "code" : "111",
    "display" : "rotaviirusnakkus",
    "property" : [ {
      "code" : "status",
      "valueCode" : "active"
    } ]
  }, {
    "code" : "201",
    "display" : "A-viirushepatiit",
    "property" : [ {
      "code" : "status",
      "valueCode" : "active"
    } ]
  }, {
    "code" : "202",
    "display" : "gripp",
    "property" : [ {
      "code" : "status",
      "valueCode" : "active"
    } ]
  }, {
    "code" : "203",
    "display" : "HPV-nakkus",
    "property" : [ {
      "code" : "status",
      "valueCode" : "active"
    } ]
  }, {
    "code" : "204",
    "display" : "katk",
    "property" : [ {
      "code" : "status",
      "valueCode" : "active"
    } ]
  }, {
    "code" : "205",
    "display" : "kollapalavik",
    "property" : [ {
      "code" : "status",
      "valueCode" : "active"
    } ]
  }, {
    "code" : "206",
    "display" : "koolera",
    "property" : [ {
      "code" : "status",
      "valueCode" : "active"
    } ]
  }, {
    "code" : "207",
    "display" : "kõhutüüfus",
    "property" : [ {
      "code" : "status",
      "valueCode" : "active"
    } ]
  }, {
    "code" : "208",
    "display" : "marutõbi",
    "property" : [ {
      "code" : "status",
      "valueCode" : "active"
    } ]
  }, {
    "code" : "209",
    "display" : "meningokokk-infektsioon",
    "property" : [ {
      "code" : "status",
      "valueCode" : "active"
    } ]
  }, {
    "code" : "210",
    "display" : "pneumokokk-infektsioon",
    "property" : [ {
      "code" : "status",
      "valueCode" : "active"
    } ]
  }, {
    "code" : "211",
    "display" : "puukentsefaliit",
    "property" : [ {
      "code" : "status",
      "valueCode" : "active"
    } ]
  }, {
    "code" : "212",
    "display" : "siberi katk",
    "property" : [ {
      "code" : "status",
      "valueCode" : "active"
    } ]
  }, {
    "code" : "213",
    "display" : "tuulerõuged",
    "property" : [ {
      "code" : "status",
      "valueCode" : "active"
    } ]
  }, {
    "code" : "214",
    "display" : "jaapani entsefaliit",
    "property" : [ {
      "code" : "status",
      "valueCode" : "active"
    } ]
  }, {
    "code" : "215",
    "display" : "rõuged",
    "property" : [ {
      "code" : "status",
      "valueCode" : "active"
    } ]
  }, {
    "code" : "216",
    "display" : "vöötohatis",
    "property" : [ {
      "code" : "status",
      "valueCode" : "active"
    } ]
  }, {
    "code" : "217",
    "display" : "RS-viirusinfektsioon",
    "property" : [ {
      "code" : "status",
      "valueCode" : "active"
    } ]
  }, {
    "code" : "218",
    "display" : "dengue palavik",
    "property" : [ {
      "code" : "status",
      "valueCode" : "active"
    } ]
  }, {
    "code" : "219",
    "display" : "COVID-19",
    "property" : [ {
      "code" : "status",
      "valueCode" : "active"
    } ]
  }, {
    "code" : "220",
    "display" : "ahvirõuged",
    "property" : [ {
      "code" : "status",
      "valueCode" : "active"
    } ]
  } ]
}